lv_binding_rust_generator/__init__.py
lv_binding_rust_generator/__main__.py
lv_binding_rust_generator-0.2.18.dist-info/licenses/LICENSE
lv_binding_rust_generator-0.2.18.dist-info/METADATA
lv_binding_rust_generator-0.2.18.dist-info/WHEEL
lv_binding_rust_generator-0.2.18.dist-info/entry_points.txt
lv_binding_rust_generator-0.2.18.dist-info/top_level.txt
lv_binding_rust_generator-0.2.18.dist-info/RECORD
