Metadata-Version: 2.4
Name: lv_binding_rust_generator
Version: 0.2.18
Summary: Unofficial, non-intrusive Lvgl binding generator for Rust
Author-email: Junkang Yuan <yuanjunkang@gmail.com>
License-Expression: GPL-2.0-only
Requires-Python: >=3.8
License-File: LICENSE
Requires-Dist: fire>=0.5.0
Requires-Dist: toolz>=1.0.0
Dynamic: license-file
